terminotes/__init__.py
terminotes/__main__.py
terminotes/app.py
terminotes/cli.py
terminotes/config.py
terminotes/editor.py
terminotes/exporters.py
terminotes/git_sync.py
terminotes/notes_frontmatter.py
terminotes/storage.py
terminotes/services/delete.py
terminotes/services/export.py
terminotes/services/notes.py
terminotes/services/prune.py
terminotes/templates/export/html/__init__.py
terminotes/templates/export/html/index.html
terminotes/templates/export/html/note.html
terminotes/templates/export/html/search.js
terminotes/templates/export/html/styles.css
terminotes/utils/__init__.py
terminotes/utils/datetime_fmt.py
terminotes/utils/wayback.py
terminotes-0.6.2.dist-info/METADATA
terminotes-0.6.2.dist-info/WHEEL
terminotes-0.6.2.dist-info/entry_points.txt
terminotes-0.6.2.dist-info/licenses/LICENSE
terminotes-0.6.2.dist-info/RECORD
