Metadata-Version: 2.4
Name: terminotes
Version: 0.6.2
Summary: Terminal-first notes CLI with SQLite storage and git sync.
Project-URL: Homepage, https://github.com/jcapul/terminotes
Project-URL: Issues, https://github.com/jcapul/terminotes/issues
Author-email: Julien Capul <julien.capul@pm.me>
License-Expression: MIT
License-File: LICENSE
Classifier: Operating System :: OS Independent
Classifier: Programming Language :: Python :: 3
Requires-Python: >=3.13
Requires-Dist: click>=8.1.7
Requires-Dist: httpx>=0.28.1
Requires-Dist: jinja2>=3.1.6
Requires-Dist: peewee>=3.18.2
Requires-Dist: pyyaml>=6.0.2
